{
  "project_info": {
    "project_number": "962500058026",
    "project_id": "billing-app-88db0",
    "storage_bucket": "billing-app-88db0.appspot.com"
  },
  "client": [
    {
      "client_info": {
        "mobilesdk_app_id": "1:962500058026:android:b284442c2ff605e753e9d3",
        "android_client_info": {
          "package_name": "com.example.billing_app"
        }
      },
      "oauth_client": [
        {
          "client_id": "962500058026-qr3de36k3dvn4de21otfl8o5a682qlm4.apps.googleusercontent.com",
          "client_type": 3
        }
      ],
      "api_key": [
        {
          "current_key": "AIzaSyBxACjBpehFyTf7gFhjkxHh6lpg3e0HCMg"
        }
      ],
      "services": {
        "appinvite_service": {
          "other_platform_oauth_client": [
            {
              "client_id": "962500058026-qr3de36k3dvn4de21otfl8o5a682qlm4.apps.googleusercontent.com",
              "client_type": 3
            }
          ]
        }
      }
    }
  ],
  "configuration_version": "1"
}